ubnesieh/__init__.py
ubnesieh/app.py
ubnesieh/book.py
ubnesieh/tokenizer.py
ubnesieh/tools/__init__.py
ubnesieh/tools/clean_cut.py
ubnesieh/tools/progress_timing.py
ubnesieh/tools/save.py
ubnesieh/tools/sort.py
ubnesieh/tools/info/__init__.py
ubnesieh/tools/info/class_info.py
ubnesieh/tools/info/running_info.py
ubnesieh-0.0.1.dist-info/LICENSE
ubnesieh-0.0.1.dist-info/METADATA
ubnesieh-0.0.1.dist-info/WHEEL
ubnesieh-0.0.1.dist-info/top_level.txt
ubnesieh-0.0.1.dist-info/RECORD
