Metadata-Version: 2.1
Name: ubnesieh
Version: 0.0.1
Home-page: 
Author: ubnesieh
Author-email: 
License: LICENSE
Classifier: Development Status :: 3 - Alpha
Classifier: Operating System :: OS Independent
Classifier: Intended Audience :: Developers
Classifier: License :: OSI Approved :: Apache Software License
Classifier: Programming Language :: Python :: 3
Classifier: Programming Language :: Python :: 3 :: Only
Classifier: Topic :: Software Development :: Libraries
License-File: LICENSE
Requires-Dist: torch
Requires-Dist: pypinyin
Requires-Dist: tqdm
Requires-Dist: pyarrow
Requires-Dist: numpy
Requires-Dist: pandas
